dbgpkg/__init__.py
dbgpkg-1.3.8.dist-info/licenses/LICENSE
dbgpkg-1.3.8.dist-info/METADATA
dbgpkg-1.3.8.dist-info/WHEEL
dbgpkg-1.3.8.dist-info/top_level.txt
dbgpkg-1.3.8.dist-info/RECORD
