Metadata-Version: 2.4
Name: dbgpkg
Version: 1.3.8
Summary: Python Debugging Toolkit
Home-page: https://github.com/
Author: Lukasa
Author-email: me@lukasa.org
Project-URL: Bug Tracker, https://github.com/
Classifier: Programming Language :: Python :: 3
Classifier: License :: OSI Approved :: MIT License
Classifier: Operating System :: OS Independent
Requires-Python: >=3.6
License-File: LICENSE
Dynamic: author
Dynamic: author-email
Dynamic: classifier
Dynamic: description
Dynamic: description-content-type
Dynamic: home-page
Dynamic: license-file
Dynamic: project-url
Dynamic: requires-python
Dynamic: summary
